[
  { "id":"registon",       "nameUz":"Registon maydoni",           "nameRu":"Площадь Регистан",            "nameEn":"Registan Square",             "provinceId":"samarkand",     "lat":39.655,"lng":66.975, "descUz":"Samarqandning ramzi. Uch ulkan madrasa (XV–XVII asr). YUNESKO ro'yxatida." },
  { "id":"gur-amir",       "nameUz":"Gur-Amir maqbarasi",         "nameRu":"Мавзолей Гур-Эмир",           "nameEn":"Gur-e-Amir Mausoleum",        "provinceId":"samarkand",     "lat":39.660,"lng":66.965, "descUz":"Amir Temur va uning avlodlarining maqbarasi (XV asr). Ko'k gumbaz bilan mashhur." },
  { "id":"shohizinda",     "nameUz":"Shohizinda nekropoli",       "nameRu":"Некрополь Шахи-Зинда",        "nameEn":"Shah-i-Zinda Necropolis",      "provinceId":"samarkand",     "lat":39.671,"lng":66.978, "descUz":"XI–XIX asrlardagi mozorlar ansambli. 'Tirik shoh' ma'nosini anglatadi." },
  { "id":"bibi-xonim",     "nameUz":"Bibi Xonim masjidi",         "nameRu":"Мечеть Биби-Ханым",           "nameEn":"Bibi-Khanym Mosque",           "provinceId":"samarkand",     "lat":39.663,"lng":66.975, "descUz":"Amir Temur tomonidan XV asrda qurilgan ulkan jome masjidi." },
  { "id":"ulugbek-obs",    "nameUz":"Ulug'bek rasadxonasi",       "nameRu":"Обсерватория Улугбека",        "nameEn":"Ulugh Beg Observatory",        "provinceId":"samarkand",     "lat":39.675,"lng":66.990, "descUz":"XV asrda Ulug'bek tomonidan qurilgan astronomik rasadxona. Jahon fanida muhim." },
  { "id":"ark-bukhara",    "nameUz":"Ark qal'asi (Buxoro)",       "nameRu":"Крепость Арк (Бухара)",        "nameEn":"Ark Fortress (Bukhara)",       "provinceId":"bukhara",       "lat":39.776,"lng":64.416, "descUz":"Buxoro amirlari qasri. 2500 yillik tarixga ega. YUNESKO ro'yxatida." },
  { "id":"kalon-minora",   "nameUz":"Kalon minorasi",             "nameRu":"Минарет Калян",                "nameEn":"Kalon Minaret",                "provinceId":"bukhara",       "lat":39.775,"lng":64.417, "descUz":"XII asrda qurilgan 47 m balandlikdagi minora. Chingizxon ham hayrat bilan qarab qolgan." },
  { "id":"somoniylar",     "nameUz":"Somoniylar maqbarasi",       "nameRu":"Мавзолей Саманидов",           "nameEn":"Samanid Mausoleum",            "provinceId":"bukhara",       "lat":39.780,"lng":64.413, "descUz":"IX–X asrlardagi eng qadimgi islomiy yodgorlik. Samoniylar sulolasi uchun qurilgan." },
  { "id":"ichan-qala",     "nameUz":"Ichan-qal'a (Xiva)",         "nameRu":"Ичан-Кала (Хива)",             "nameEn":"Itchan Kala (Khiva)",          "provinceId":"khorezm",       "lat":41.378,"lng":60.362, "descUz":"Xivaning ichki qal'asi. XIV–XIX asr me'morchiligi. YUNESKO ro'yxatida." },
  { "id":"pahlavon-mahmud","nameUz":"Pahlavon Mahmud maqbarasi",  "nameRu":"Мавзолей Пахлавана Махмуда",   "nameEn":"Pahlavon Mahmud Mausoleum",   "provinceId":"khorezm",       "lat":41.379,"lng":60.361, "descUz":"XIV asr shoiri va polvoni Pahlavon Mahmudga bag'ishlangan maqbara. Xivaning markaziy ziyoratgohi." },
  { "id":"kokaldosh",      "nameUz":"Ko'kaldosh madrasasi",       "nameRu":"Медресе Кукальдаш",            "nameEn":"Kukaldosh Madrasa",            "provinceId":"tashkent-city", "lat":41.327,"lng":69.240, "descUz":"Toshkentning XVI asrda qurilgan tarixiy madrasasi. Shahar markazida." },
  { "id":"xast-imom",      "nameUz":"Xast Imom majmuasi",         "nameRu":"Комплекс Хаст-Имам",           "nameEn":"Khast Imam Complex",           "provinceId":"tashkent-city", "lat":41.332,"lng":69.238, "descUz":"Toshkentning diniy markazi. Dunyo tarixidagi eng qadimiy Qur'on nusxasi saqlangan." },
  { "id":"qoratepa",       "nameUz":"Qoratepa budda ibodatxonasi","nameRu":"Буддийский храм Кара-Тепа",    "nameEn":"Kara Tepa Buddhist Temple",    "provinceId":"surkhandarya",  "lat":37.245,"lng":67.278, "descUz":"Termiz yaqinidagi I–III asrga oid budda monastiri. O'rta Osiyodagi eng qadimiy buddist yodgorlik." },
  { "id":"fayoztepa",      "nameUz":"Fayoztepa budda ibodatxonasi","nameRu":"Буддийский храм Фаёзтепа",   "nameEn":"Fayaz Tepa Buddhist Temple",   "provinceId":"surkhandarya",  "lat":37.220,"lng":67.275, "descUz":"Termiz yaqinidagi I–VII asrga oid budda ibodatxonasi. Chiroyli freska va haykallar topilgan." },
  { "id":"jarqurgon",      "nameUz":"Jarqo'rg'on minorasi",       "nameRu":"Минарет Джаркурган",           "nameEn":"Jarkurgan Minaret",            "provinceId":"surkhandarya",  "lat":37.532,"lng":67.419, "descUz":"XII asrda qurilgan 21 m balandlikdagi minora. O'rta Osiyodagi eng go'zal minaralardan biri." },
  { "id":"oq-saroy",       "nameUz":"Oq-Saroy xarobalari",        "nameRu":"Развалины Ак-Сарая",           "nameEn":"Ak-Saray Palace Ruins",        "provinceId":"kashkadarya",   "lat":39.057,"lng":66.839, "descUz":"Shahrisabzdagi Amir Temurning yozgi saroyi (XIV–XV asr). 'Oq saroylar' deyilgan." },
  { "id":"dor-tilovat",    "nameUz":"Dor ul-Tilovat majmuasi",    "nameRu":"Комплекс Дор-ут-Тиловат",     "nameEn":"Dor ul-Tilovat Complex",       "provinceId":"kashkadarya",   "lat":39.058,"lng":66.840, "descUz":"Shahrisabzdagi masjid va maqbara majmuasi. Temuriylar davri me'morchiligi." },
  { "id":"nurota-ziyorat", "nameUz":"Nurota ziyoratgohi",         "nameRu":"Святилище Нурата",             "nameEn":"Nurata Shrine",                "provinceId":"navoi",         "lat":40.558,"lng":65.685, "descUz":"Aleksandr Makedonskiy tomonidan qurilgan qal'a xarobalari va qadimiy masjid." },
  { "id":"raboti-malik",   "nameUz":"Raboti Malik karvonsaroyi",  "nameRu":"Каравансарай Рабат-и-Малик",   "nameEn":"Rabat-i Malik Caravanserai",   "provinceId":"navoi",         "lat":40.190,"lng":65.000, "descUz":"XI asrda qurilgan Buyuk ipak yo'lidagi ulkan karvonsaroy. Navoiy viloyatida." },
  { "id":"afrosiyob",      "nameUz":"Afrosiyob arxeologik maydoni","nameRu":"Афрасиаб (городище)",         "nameEn":"Afrasiab Archaeological Site", "provinceId":"samarkand",     "lat":39.671,"lng":66.975, "descUz":"Qadimiy Samarqand joylashgan tepalik. Miloddan avvalgi VII asrdan boshlab aholi yashagan." }
]
